LICENSE.txt
MANIFEST.in
README.md
setup.cfg
setup.py
bacphlip/__init__.py
bacphlip/bacphlip.py
bacphlip/command_line.py
bacphlip.egg-info/PKG-INFO
bacphlip.egg-info/SOURCES.txt
bacphlip.egg-info/dependency_links.txt
bacphlip.egg-info/entry_points.txt
bacphlip.egg-info/requires.txt
bacphlip.egg-info/top_level.txt
bacphlip/data/prot_models.hmm
bacphlip/data/rf_best.joblib
bacphlip/data/example_data/genome_example.fasta
bacphlip/data/example_data/genome_example.fasta.6frame
bacphlip/data/example_data/genome_example.fasta.bacphlip
bacphlip/data/example_data/genome_example.fasta.hmmsearch
bacphlip/data/example_data/genome_example.fasta.hmmsearch.tsv
bacphlip/data/example_data/genome_example_2.fasta
bacphlip/data/example_data/genome_example_2.fasta.6frame
bacphlip/data/example_data/genome_example_2.fasta.bacphlip
bacphlip/data/example_data/genome_example_2.fasta.hmmsearch
bacphlip/data/example_data/genome_example_2.fasta.hmmsearch.tsv
bacphlip/data/example_data/multi_example.fasta
bacphlip/data/example_data/multi_example.fasta.bacphlip
bacphlip/data/example_data/multi_example.fasta.hmmsearch.tsv
bacphlip/data/example_data/multi_example.fasta.BACPHLIP_DIR/NC_001416.1.6frame
bacphlip/data/example_data/multi_example.fasta.BACPHLIP_DIR/NC_001416.1.hmmsearch
bacphlip/data/example_data/multi_example.fasta.BACPHLIP_DIR/NC_001416.1.hmmsearch.tsv
bacphlip/data/example_data/multi_example.fasta.BACPHLIP_DIR/NC_001604.1.6frame
bacphlip/data/example_data/multi_example.fasta.BACPHLIP_DIR/NC_001604.1.hmmsearch
bacphlip/data/example_data/multi_example.fasta.BACPHLIP_DIR/NC_001604.1.hmmsearch.tsv