Metadata-Version: 2.1
Name: bacphlip
Version: 0.9.6
Summary: A Random Forest classifier to predict bacteriophage lifestyle
Home-page: https://github.com/adamhockenberry/bacphlip
Author: Adam J Hockenberry
Author-email: adam.hockenberry@utexas.edu
License: UNKNOWN
Platform: UNKNOWN
Classifier: Programming Language :: Python :: 3
Classifier: License :: OSI Approved :: MIT License
Classifier: Operating System :: OS Independent
Classifier: Topic :: Scientific/Engineering :: Bio-Informatics
Classifier: Intended Audience :: Science/Research
Requires-Python: >=3.6
